qhoptim/__init__.py
qhoptim/common/__init__.py
qhoptim/common/param_conv.py
qhoptim/pyt/__init__.py
qhoptim/pyt/qhadam.py
qhoptim/pyt/qhm.py
qhoptim/tf/__init__.py
qhoptim/tf/qhadam.py
qhoptim/tf/qhm.py
qhoptim/tf/util.py
qhoptim-1.0.0.data/data/source_docs/qhoptim/CODE_OF_CONDUCT.rst
qhoptim-1.0.0.data/data/source_docs/qhoptim/CONTRIBUTING.rst
qhoptim-1.0.0.data/data/source_docs/qhoptim/LICENSE
qhoptim-1.0.0.data/data/source_docs/qhoptim/README.rst
qhoptim-1.0.0.dist-info/LICENSE
qhoptim-1.0.0.dist-info/METADATA
qhoptim-1.0.0.dist-info/WHEEL
qhoptim-1.0.0.dist-info/top_level.txt
qhoptim-1.0.0.dist-info/zip-safe
qhoptim-1.0.0.dist-info/RECORD
