Metadata-Version: 2.1
Name: qhoptim
Version: 1.0.0
Summary: Quasi-hyperbolic optimization algorithms from Facebook AI Research.
Home-page: https://github.com/facebookresearch/qhoptim
Author: Facebook AI Research
Author-email: UNKNOWN
License: MIT
Platform: UNKNOWN
